tree_creator/__init__.py
tree_creator/_version.py
tree_creator/core.py
tree_creator-1.1.3.dist-info/licenses/LICENSE
tree_creator-1.1.3.dist-info/METADATA
tree_creator-1.1.3.dist-info/WHEEL
tree_creator-1.1.3.dist-info/entry_points.txt
tree_creator-1.1.3.dist-info/top_level.txt
tree_creator-1.1.3.dist-info/RECORD
