Metadata-Version: 2.4
Name: tree-creator
Version: 1.1.3
Summary: Create directory and file structures from tree-like text representations
Home-page: https://github.com/jack-low/tree-creator
Author: Jack3Low
Author-email: xapa.pw@gmail.com
License: MIT
Project-URL: Bug Reports, https://github.com/jack-low/tree-creator/issues
Project-URL: Source, https://github.com/jack-low/tree-creator
Project-URL: Documentation, https://github.com/jack-low/tree-creator#readme
Project-URL: Japanese README, https://github.com/jack-low/tree-creator/blob/main/README.ja.md
Keywords: tree directory structure filesystem generator creator
Classifier: Development Status :: 5 - Production/Stable
Classifier: Intended Audience :: Developers
Classifier: Topic :: Software Development :: Libraries :: Python Modules
Classifier: Topic :: System :: Filesystems
Classifier: License :: OSI Approved :: MIT License
Classifier: Programming Language :: Python :: 3
Classifier: Programming Language :: Python :: 3.7
Classifier: Programming Language :: Python :: 3.8
Classifier: Programming Language :: Python :: 3.9
Classifier: Programming Language :: Python :: 3.10
Classifier: Programming Language :: Python :: 3.11
Classifier: Programming Language :: Python :: 3.12
Classifier: Operating System :: OS Independent
Requires-Python: >=3.7
License-File: LICENSE
Provides-Extra: dev
Requires-Dist: pytest>=7.0; extra == "dev"
Requires-Dist: pytest-cov>=4.0; extra == "dev"
Requires-Dist: black>=23.0; extra == "dev"
Requires-Dist: flake8>=6.0; extra == "dev"
Requires-Dist: mypy>=1.0; extra == "dev"
Dynamic: author
Dynamic: author-email
Dynamic: classifier
Dynamic: description
Dynamic: description-content-type
Dynamic: home-page
Dynamic: keywords
Dynamic: license
Dynamic: license-file
Dynamic: project-url
Dynamic: provides-extra
Dynamic: requires-python
Dynamic: summary
